pyutil_mk1/__init__.py
pyutil_mk1/arg_util.py
pyutil_mk1/dict_string_util.py
pyutil_mk1/extract_urls.py
pyutil_mk1/find_children_dirs_containing_files.py
pyutil_mk1/find_dirs_containing_content.py
pyutil_mk1/fs_util.py
pyutil_mk1/jsonrw.py
pyutil_mk1/parse_file_lines.py
pyutil_mk1/path_util.py
pyutil_mk1/platform_bind_util.py
pyutil_mk1/random_files.py
pyutil_mk1/time_conversion_util.py
pyutil_mk1/web_tool.py
pyutilmk1/__init__.py
pyutilmk1/arg_util.py
pyutilmk1/dict_string_util.py
pyutilmk1/extract_urls.py
pyutilmk1/find_children_dirs_containing_files.py
pyutilmk1/find_dirs_containing_content.py
pyutilmk1/fs_util.py
pyutilmk1/jsonrw.py
pyutilmk1/parse_file_lines.py
pyutilmk1/path_util.py
pyutilmk1/platform_bind_util.py
pyutilmk1/random_files.py
pyutilmk1/time_conversion_util.py
pyutilmk1/web_tool.py
pyutilmk1-0.0.2.dist-info/LICENSE.txt
pyutilmk1-0.0.2.dist-info/METADATA
pyutilmk1-0.0.2.dist-info/WHEEL
pyutilmk1-0.0.2.dist-info/top_level.txt
pyutilmk1-0.0.2.dist-info/RECORD
