Metadata-Version: 2.1
Name: pyutilmk1
Version: 0.0.2
Summary: Small utilities for path, strings, fs, dict, .etc manipulation. mark1
Home-page: https://github.com/markuspeitl/pyutilmk1
Author: Markus Peitl
Author-email: office@markuspeitl.com
Classifier: Programming Language :: Python :: 3
Classifier: Intended Audience :: Developers
Classifier: Natural Language :: English
Classifier: License :: OSI Approved :: MIT License
Classifier: Topic :: Software Development
Classifier: Topic :: Software Development :: Libraries
Requires-Python: >=3
License-File: LICENSE.txt
Requires-Dist: tldextract
Requires-Dist: pyperclip
Requires-Dist: zstd
